e2e/__init__.py
e2e/conftest.py
e2e/pages.py
e2e/test_mfa.py
example_projects/__init__.py
piccolo_api/__init__.py
piccolo_api/py.typed
piccolo_api/change_password/__init__.py
piccolo_api/change_password/endpoints.py
piccolo_api/crud/__init__.py
piccolo_api/crud/endpoints.py
piccolo_api/crud/exceptions.py
piccolo_api/crud/hooks.py
piccolo_api/crud/serializers.py
piccolo_api/crud/validators.py
piccolo_api/csp/__init__.py
piccolo_api/csp/middleware.py
piccolo_api/csrf/__init__.py
piccolo_api/csrf/middleware.py
piccolo_api/encryption/__init__.py
piccolo_api/encryption/providers.py
piccolo_api/fastapi/__init__.py
piccolo_api/fastapi/endpoints.py
piccolo_api/jwt_auth/__init__.py
piccolo_api/jwt_auth/endpoints.py
piccolo_api/jwt_auth/middleware.py
piccolo_api/media/__init__.py
piccolo_api/media/base.py
piccolo_api/media/content_type.py
piccolo_api/media/local.py
piccolo_api/media/s3.py
piccolo_api/mfa/__init__.py
piccolo_api/mfa/endpoints.py
piccolo_api/mfa/provider.py
piccolo_api/mfa/recovery_codes.py
piccolo_api/mfa/authenticator/__init__.py
piccolo_api/mfa/authenticator/piccolo_app.py
piccolo_api/mfa/authenticator/provider.py
piccolo_api/mfa/authenticator/tables.py
piccolo_api/mfa/authenticator/utils.py
piccolo_api/mfa/authenticator/piccolo_migrations/__init__.py
piccolo_api/mfa/authenticator/piccolo_migrations/mfa_authenticator_2024_08_08t21_41_46_837552.py
piccolo_api/openapi/__init__.py
piccolo_api/openapi/endpoints.py
piccolo_api/openapi/templates/swagger_ui.html.jinja
piccolo_api/rate_limiting/__init__.py
piccolo_api/rate_limiting/middleware.py
piccolo_api/register/__init__.py
piccolo_api/register/endpoints.py
piccolo_api/session_auth/__init__.py
piccolo_api/session_auth/commands.py
piccolo_api/session_auth/endpoints.py
piccolo_api/session_auth/middleware.py
piccolo_api/session_auth/piccolo_app.py
piccolo_api/session_auth/tables.py
piccolo_api/session_auth/piccolo_migrations/2019-11-12T20-47-17.py
piccolo_api/session_auth/piccolo_migrations/__init__.py
piccolo_api-1.7.0.dist-info/licenses/LICENSE
piccolo_api-1.7.0.dist-info/METADATA
piccolo_api-1.7.0.dist-info/WHEEL
piccolo_api-1.7.0.dist-info/top_level.txt
piccolo_api-1.7.0.dist-info/RECORD
