Metadata-Version: 2.4
Name: piccolo_api
Version: 1.7.0
Summary: Utilities for using the Piccolo ORM in ASGI apps, plus essential ASGI middleware such as authentication and rate limiting.
Home-page: https://github.com/piccolo-orm/piccolo_api
Author: Daniel Townsend
Author-email: dan@dantownsend.co.uk
License: MIT
Classifier: License :: OSI Approved :: MIT License
Classifier: Programming Language :: Python
Classifier: Programming Language :: Python :: 3
Classifier: Programming Language :: Python :: 3.9
Classifier: Programming Language :: Python :: 3.10
Classifier: Programming Language :: Python :: 3.11
Classifier: Programming Language :: Python :: 3.12
Classifier: Programming Language :: Python :: 3.13
Classifier: Programming Language :: Python :: Implementation :: CPython
Requires-Python: >=3.9.0
License-File: LICENSE
Requires-Dist: Jinja2>=2.11.0
Requires-Dist: piccolo[postgres]>=1.16.0
Requires-Dist: pydantic[email]>=2.0
Requires-Dist: python-multipart>=0.0.5
Requires-Dist: fastapi>=0.100.0
Requires-Dist: PyJWT>=2.0.0
Requires-Dist: httpx>=0.20.0
Provides-Extra: authenticator
Requires-Dist: pyotp==2.9.0; extra == "authenticator"
Requires-Dist: qrcode==7.4.2; extra == "authenticator"
Provides-Extra: cryptography
Requires-Dist: cryptography==45.0.2; extra == "cryptography"
Provides-Extra: pynacl
Requires-Dist: PyNaCl==1.5.0; extra == "pynacl"
Provides-Extra: s3
Requires-Dist: boto3==1.*; extra == "s3"
Provides-Extra: all
Requires-Dist: pyotp==2.9.0; extra == "all"
Requires-Dist: qrcode==7.4.2; extra == "all"
Requires-Dist: cryptography==45.0.2; extra == "all"
Requires-Dist: PyNaCl==1.5.0; extra == "all"
Requires-Dist: boto3==1.*; extra == "all"
Dynamic: author
Dynamic: author-email
Dynamic: classifier
Dynamic: description
Dynamic: description-content-type
Dynamic: home-page
Dynamic: license
Dynamic: license-file
Dynamic: provides-extra
Dynamic: requires-dist
Dynamic: requires-python
Dynamic: summary
